LICENSE
MANIFEST.in
README.md
requirements.txt
setup.cfg
setup.py
versioneer.py
clinvar_tsv/Snakefile
clinvar_tsv/__init__.py
clinvar_tsv/__main__.py
clinvar_tsv/_version.py
clinvar_tsv/common.py
clinvar_tsv/exceptions.py
clinvar_tsv/merge_tsvs.py
clinvar_tsv/normalize.py
clinvar_tsv/parse_clinvar_xml.py
clinvar_tsv.egg-info/PKG-INFO
clinvar_tsv.egg-info/SOURCES.txt
clinvar_tsv.egg-info/dependency_links.txt
clinvar_tsv.egg-info/entry_points.txt
clinvar_tsv.egg-info/not-zip-safe
clinvar_tsv.egg-info/requires.txt
clinvar_tsv.egg-info/top_level.txt
requirements/base.txt
requirements/dev.txt
requirements/test.txt
tests/conftest.py
tests/test_merge_tsvs.py
tests/test_parse_xml_small.py
tests/test_parse_xml_sv.py
tests/data/README.md
tests/data/clinvar-74722873.xml
tests/data/clinvar-92148661.xml
tests/data/clinvar-in-context-74722873.xml
tests/data/clinvar-spta1.xml
tests/data/parsed-74722873.37.tsv
tests/data/parsed-in-context-74722873.37.tsv
tests/data/parsed-spta1.37.tsv