Metadata-Version: 2.1
Name: clinvar-tsv
Version: 0.6.0
Summary: Python 3 library for accessing and managing BioMedical sheets
Home-page: https://github.com/bihealth/clinvar-tsv
Author: Manuel Holtgrewe
Author-email: manuel.holtgrewe@bihealth.de
License: MIT license
Keywords: clinvar
Classifier: Development Status :: 2 - Pre-Alpha
Classifier: Intended Audience :: Developers
Classifier: License :: OSI Approved :: MIT License
Classifier: Natural Language :: English
Classifier: Programming Language :: Python :: 3
Classifier: Programming Language :: Python :: 3.8
Classifier: Programming Language :: Python :: 3.9
Classifier: Programming Language :: Python :: 3.10
License-File: LICENSE
